odoo8_addon_mail_tracking_mass_mailing-8.0.1.0.1-py2.7-nspkg.pth
odoo_addons/mail_tracking_mass_mailing/__openerp__.py
odoo_addons/mail_tracking_mass_mailing/hooks.py
odoo_addons/mail_tracking_mass_mailing/__init__.py
odoo_addons/mail_tracking_mass_mailing/README.rst
odoo_addons/mail_tracking_mass_mailing/models/mail_mass_mailing_contact.py
odoo_addons/mail_tracking_mass_mailing/models/mail_tracking_email.py
odoo_addons/mail_tracking_mass_mailing/models/mail_mail.py
odoo_addons/mail_tracking_mass_mailing/models/mail_mail_statistics.py
odoo_addons/mail_tracking_mass_mailing/models/__init__.py
odoo_addons/mail_tracking_mass_mailing/models/mail_tracking_event.py
odoo_addons/mail_tracking_mass_mailing/models/mail_mass_mailing.py
odoo_addons/mail_tracking_mass_mailing/i18n/es.po
odoo_addons/mail_tracking_mass_mailing/i18n/ca.po
odoo_addons/mail_tracking_mass_mailing/i18n/es_CO.po
odoo_addons/mail_tracking_mass_mailing/i18n/sl.po
odoo_addons/mail_tracking_mass_mailing/i18n/de.po
odoo_addons/mail_tracking_mass_mailing/i18n/fr.po
odoo_addons/mail_tracking_mass_mailing/i18n/pt_BR.po
odoo_addons/mail_tracking_mass_mailing/views/mail_mass_mailing_contact_view.xml
odoo_addons/mail_tracking_mass_mailing/views/mail_mail_statistics_view.xml
odoo_addons/mail_tracking_mass_mailing/views/mail_mass_mailing_view.xml
odoo_addons/mail_tracking_mass_mailing/views/mail_tracking_email_view.xml
odoo_addons/mail_tracking_mass_mailing/tests/__init__.py
odoo_addons/mail_tracking_mass_mailing/tests/test_mass_mailing.py
odoo_addons/mail_tracking_mass_mailing/static/description/icon.png
odoo8_addon_mail_tracking_mass_mailing-8.0.1.0.1.dist-info/top_level.txt
odoo8_addon_mail_tracking_mass_mailing-8.0.1.0.1.dist-info/WHEEL
odoo8_addon_mail_tracking_mass_mailing-8.0.1.0.1.dist-info/RECORD
odoo8_addon_mail_tracking_mass_mailing-8.0.1.0.1.dist-info/metadata.json
odoo8_addon_mail_tracking_mass_mailing-8.0.1.0.1.dist-info/DESCRIPTION.rst
odoo8_addon_mail_tracking_mass_mailing-8.0.1.0.1.dist-info/METADATA
odoo8_addon_mail_tracking_mass_mailing-8.0.1.0.1.dist-info/namespace_packages.txt
