Metadata-Version: 2.0
Name: odoo8-addon-mail-tracking-mass-mailing
Version: 8.0.1.0.1
Summary: Improve mass mailing email tracking
Home-page: http://www.tecnativa.com
Author: UNKNOWN
Author-email: UNKNOWN
License: AGPL-3
Platform: UNKNOWN
Requires-Dist: odoo (<9.0a,>=8.0a)
Requires-Dist: odoo8-addon-mail-tracking
Classifier: Programming Language :: Python :: 2.7
Classifier: Framework :: Odoo
Classifier: License :: OSI Approved :: GNU Affero General Public License v3
